watchify/__init__.py
watchify/exceptions.py
watchify/functions.py
watchify/interfaces.py
watchify/logger.py
watchify/spies.py
watchify/watchers.py
watchify-0.2.0.dist-info/LICENSE.md
watchify-0.2.0.dist-info/METADATA
watchify-0.2.0.dist-info/WHEEL
watchify-0.2.0.dist-info/RECORD
