Metadata-Version: 2.1
Name: watchify
Version: 0.2.0
Summary: Decoupled event-driven communication between objects.
Home-page: https://github.com/daniel-augustus/watchify
License: MIT
Keywords: watchify,observer,decoupled,listeners,event-driven,objects communication
Author: Daniel Augusto
Author-email: dev.daniel.augusto@gmail.com
Requires-Python: >=3.8.1,<4.0.0
Classifier: Intended Audience :: Developers
Classifier: Intended Audience :: Information Technology
Classifier: Intended Audience :: System Administrators
Classifier: License :: OSI Approved :: MIT License
Classifier: Programming Language :: Python
Classifier: Programming Language :: Python :: 3
Classifier: Programming Language :: Python :: 3.9
Classifier: Programming Language :: Python :: 3.10
Classifier: Programming Language :: Python :: 3.11
Classifier: Programming Language :: Python :: 3.12
Classifier: Programming Language :: Python :: 3.8
Classifier: Topic :: Software Development
Classifier: Topic :: Software Development :: Libraries
Classifier: Topic :: Software Development :: Libraries :: Python Modules
Classifier: Topic :: Utilities
Classifier: Typing :: Typed
Project-URL: Repository, https://github.com/daniel-augustus/watchify
